webengage_automation/__init__.py
webengage_automation/logger.py
webengage_automation_app-0.1.0.dist-info/METADATA
webengage_automation_app-0.1.0.dist-info/WHEEL
webengage_automation_app-0.1.0.dist-info/entry_points.txt
webengage_automation_app-0.1.0.dist-info/top_level.txt
webengage_automation_app-0.1.0.dist-info/RECORD
